pratts/__init__.py
pratts/pratts.py
pratts-0.1.0.dist-info/licenses/LICENSE
pratts-0.1.0.dist-info/METADATA
pratts-0.1.0.dist-info/WHEEL
pratts-0.1.0.dist-info/top_level.txt
pratts-0.1.0.dist-info/RECORD
